MANIFEST.in
README.rst
config-template.yaml
setup.py
metzoo/__init__.py
metzoo/writer/__init__.py
metzoo/writer/writer.py
metzoo_python_writer.egg-info/PKG-INFO
metzoo_python_writer.egg-info/SOURCES.txt
metzoo_python_writer.egg-info/dependency_links.txt
metzoo_python_writer.egg-info/entry_points.txt
metzoo_python_writer.egg-info/not-zip-safe
metzoo_python_writer.egg-info/requires.txt
metzoo_python_writer.egg-info/top_level.txt